<!DOCTYPE files>
<FolderProperties FolderName=".">
 <Folders/>
 <Files>
  <FileProperties md5="fd0b78eeba106fad6816b8d1d5b760ee" FileName="CrashRpt.dll" Size="6884864"/>
  <FileProperties md5="3fa52de9055183037465c37913daf7a0" FileName="d3dx11d.dll" Size="4760064"/>
  <FileProperties md5="26af232140c88b42d92a88f2198edf6a" FileName="d3dx9_32.dll" Size="3426072"/>
  <FileProperties md5="1ca939918ed1b930059b3a882de6f648" FileName="d3dx9_34.dll" Size="3497832"/>
  <FileProperties md5="44bfec5c9c82a2ee9871d88fd3b9a0e2" FileName="d3dx9_36.dll" Size="3734536"/>
  <FileProperties md5="d90590446cb7b8ba4176672c9082c74f" FileName="msvcp100.dll" Size="431936"/>
  <FileProperties md5="0e8888aadab9669d06f55767f2ccaf7b" FileName="msvcr100.dll" Size="758592"/>
  <FileProperties md5="a8bb1d83bf5accd6928e9380c1050176" FileName="PurifierB.dll" Size="2719744"/>
  <FileProperties md5="caa265f1e3e0d0baf59142b2ee845111" FileName="RF.exe" Size="8957952"/>
  <FileProperties md5="bfbdb9e05d9dfbd5cc96a5aaa78a8772" FileName="RF_Online.bin" Size="8738816"/>
 </Files>
 <FolderProperties FolderName="Chef">
  <Folders/>
  <Files>
   <FileProperties md5="29450374fbda61be3696aafeefc0bcda" FileName="Monster.ini" Size="50751"/>
  </Files>
 </FolderProperties>
 <FolderProperties FolderName="DataTable">
  <Folders/>
  <Files>
   <FileProperties md5="f44ce15564dd03279f1c7cc7f1ebd60f" FileName="AccessoryGradeUpEff.edf" Size="255913"/>
   <FileProperties md5="1f262bcb59e520337388bffb24bf903b" FileName="Character.edf" Size="739037"/>
   <FileProperties md5="7c415f22ac08a69aeff57bf77ef1df9d" FileName="CloakGradeUpEff.edf" Size="255913"/>
   <FileProperties md5="1c1f7f9d2221a58fcf99709003ea0714" FileName="DefendGradeUpEff.edf" Size="255913"/>
   <FileProperties md5="b639eb705020693a245d79b9d2f73d47" FileName="DefendRankUpEff.edf" Size="39061"/>
   <FileProperties md5="8350939231099d2f21277cb3f96d81cd" FileName="EventShip.edf" Size="41609"/>
   <FileProperties md5="5b262c6438064fe52269f3b8f9ccf5d9" FileName="EventSound.edf" Size="361"/>
   <FileProperties md5="e742494d8a518bfccd279d8cbb5abdd2" FileName="ForceItemLink.edf" Size="6221"/>
   <FileProperties md5="de665d7dc325757c8ac6e9a48c8b38c4" FileName="item.edf" Size="4182481"/>
   <FileProperties md5="3f67527dbf5248449755ccc6a661043e" FileName="ItemCash.edf" Size="297"/>
   <FileProperties md5="a737ee02d1af1f9942c3d9361e668027" FileName="ItemCombine.edf" Size="3368657"/>
   <FileProperties md5="a7815e25f041f94336aa6cea79f26a04" FileName="ItemCostumeLink.edf" Size="493"/>
   <FileProperties md5="d07f5ecea7f9c11738af5ce2f8b647dd" FileName="ItemPremium.edf" Size="384385"/>
   <FileProperties md5="05e250b967e06fd2abae8ba63cf5375e" FileName="ItemSetEffect.edf" Size="460377"/>
   <FileProperties md5="bb62ebc70c0e3c2a088c074f03e294d9" FileName="ItemTimer.edf" Size="44409"/>
   <FileProperties md5="97f1e023e19662ca4598894e82cab22f" FileName="Map.edf" Size="270868"/>
   <FileProperties md5="15a7a2b18e035f08533300fcce26db5a" FileName="MinerGradeUpEff.edf" Size="39501"/>
   <FileProperties md5="f7e656094f0250794a1bd05926c81e71" FileName="MsgEvent.edf" Size="8181"/>
   <FileProperties md5="d6d5fb083a3cc186fcaec7a45fa012b8" FileName="PlayerCharacter.edf" Size="657"/>
   <FileProperties md5="ad15d9db4243d83000b78285a4330aa8" FileName="Quest.edf" Size="1442653"/>
   <FileProperties md5="6c06e3a0f2d8e86bd5daf0959d7434f0" FileName="Resource.edf" Size="7972337"/>
   <FileProperties md5="7b9dbe91f3bfb38a4210f1903b651de4" FileName="ShieldGradeUpEff.edf" Size="255913"/>
   <FileProperties md5="30cc792d01882072d7e062beac55d4ee" FileName="SkillForce.edf" Size="1522361"/>
   <FileProperties md5="ff692df706e3534f0df6e68da165ba7d" FileName="SpecialStore.edf" Size="469473"/>
   <FileProperties md5="b30addfae807a62aef9e0f1e1768d84d" FileName="Store.edf" Size="633105"/>
   <FileProperties md5="a3f16e21157c7e26ca61ae4ff48e3045" FileName="TrunkExted.edf" Size="737"/>
   <FileProperties md5="67f819ab6c556f4fe65174623963ee92" FileName="WeaponGradeUpEff.edf" Size="255913"/>
   <FileProperties md5="2677d362fcf4b174438f5af36254f414" FileName="WeaponRankUpEff.edf" Size="39061"/>
  </Files>
  <FolderProperties FolderName="en-gb">
   <Folders/>
   <Files>
    <FileProperties md5="7e0f228854a4164ed9d1c00d48feeb61" FileName="NDCharacter.edf" Size="232833"/>
    <FileProperties md5="e29cbb1f949a891e716fc33544701f50" FileName="NDEventShip.edf" Size="12486"/>
    <FileProperties md5="721ed131e8f28ce97e7c73ea3ebd1870" FileName="nditem.edf" Size="6378747"/>
    <FileProperties md5="914e7b496d22edf34005ca95141e51a3" FileName="NDItemCash.edf" Size="297"/>
    <FileProperties md5="bebd99d5d348a405bd08a0ff4e71eb68" FileName="NDLanguage.edf" Size="257046"/>
    <FileProperties md5="587795e13718a101da37aa3dee99137e" FileName="NDMap.edf" Size="43962"/>
    <FileProperties md5="bd40ba7d22e91a7d2472f096547fde65" FileName="NDMsgEvent.edf" Size="7977"/>
    <FileProperties md5="6fc861e0988093195416fb01a994f604" FileName="NDMsgMonster.edf" Size="73030"/>
    <FileProperties md5="c4205084073f7ac42d7962744e4c3be5" FileName="NDQuest.edf" Size="763517"/>
    <FileProperties md5="50666876d5d781dccf2f0e8dd08e7006" FileName="NDSkillForce.edf" Size="1219977"/>
    <FileProperties md5="6256aecfa86d144432cecb796cebeda1" FileName="NDStore.edf" Size="74625"/>
    <FileProperties md5="2a5a63e8c6c60af3d4dfd52fbdd203c5" FileName="NDUIHelp.edf" Size="996137"/>
   </Files>
  </FolderProperties>
  <FolderProperties FolderName="ko-kr">
   <Folders/>
   <Files>
    <FileProperties md5="68d8d15aa1dd780c9f0b49f036be8d33" FileName="Aka.dic" Size="11349"/>
    <FileProperties md5="fc41fb81d45fd2fb22e4425f75820fda" FileName="Ika.dic" Size="41"/>
   </Files>
  </FolderProperties>
  <FolderProperties FolderName="ru-ru">
   <Folders/>
   <Files>
    <FileProperties md5="d97684643c3c5ae175ca296b126d1409" FileName="advr.dat" Size="20104"/>
    <FileProperties md5="68d8d15aa1dd780c9f0b49f036be8d33" FileName="Aka.dic" Size="11349"/>
    <FileProperties md5="62afafc3b06d8a425fe80259fa27fb2d" FileName="AR.scp" Size="28755"/>
    <FileProperties md5="aac6f6cc78c7941fafd92d9a729e2fed" FileName="AS.scp" Size="28792"/>
    <FileProperties md5="a5e85de3a3cbda1705773a91f6b4a42c" FileName="AW.scp" Size="27208"/>
    <FileProperties md5="aa6a9261fa57c328064a0fd41c111922" FileName="BF.scp" Size="29135"/>
    <FileProperties md5="a9f68c1771537af49d31c314866ff3bd" FileName="BR.scp" Size="28727"/>
    <FileProperties md5="cf609ebbd72cb9f7058845cb58f4151f" FileName="BS.scp" Size="28726"/>
    <FileProperties md5="0ec8088f2be3fdecfaa791f2ecbdb977" FileName="BW.scp" Size="27185"/>
    <FileProperties md5="f911310311f2f714c58a3d2077f9238c" FileName="cashshopcategory.dat" Size="805"/>
    <FileProperties md5="8e1242ed92ef67103f37716bf47ea0d3" FileName="CcrLogo.dat" Size="183"/>
    <FileProperties md5="508c56f3332e4a939308189d4e6d98d4" FileName="cf.scp" Size="29179"/>
    <FileProperties md5="1aa14eb2020e21137643b19c9b24ef92" FileName="ChatCommand.ini" Size="2941"/>
    <FileProperties md5="d641a69a9b06e02a1b74a3b9375b0fe0" FileName="cr.scp" Size="28733"/>
    <FileProperties md5="192e4afaac9c9ecd6666acb65be1c177" FileName="cryp.dat" Size="38384"/>
    <FileProperties md5="18fe388b1f9ea739ed1f7f2c6478a513" FileName="CS.scp" Size="27200"/>
    <FileProperties md5="4de35c3e04e446d1737efab7752666fc" FileName="Cska.txt" Size="2265"/>
    <FileProperties md5="cb2ff112de421862f62c460db9c45ae7" FileName="CW.scp" Size="27209"/>
    <FileProperties md5="d1d7cceb9cd295834ab3211d12564438" FileName="font.ini" Size="25"/>
    <FileProperties md5="fc41fb81d45fd2fb22e4425f75820fda" FileName="Ika.dic" Size="41"/>
    <FileProperties md5="978bf349d8a38f34da0bb7df2c861457" FileName="KeyMap.dat" Size="1968"/>
    <FileProperties md5="840e0897b4b8cb724dc531740e48ea59" FileName="KeyMap_NKM.dat" Size="1885"/>
    <FileProperties md5="ad9600617151b3f12268da6d6843a97c" FileName="MAPDATA.DAT" Size="251443"/>
    <FileProperties md5="c7118c25b0cd98db91100dd98e532813" FileName="ndcharacter.edf" Size="232833"/>
    <FileProperties md5="933c785365bcd7101b729d138400f088" FileName="nditem.edf" Size="6394016"/>
    <FileProperties md5="5a320dafabddf840bb085d2639f07331" FileName="nditemcash.edf" Size="297"/>
    <FileProperties md5="6fe681b47285fcee24cf16c0bae92d56" FileName="ndlanguage.edf" Size="267525"/>
    <FileProperties md5="78187979be18d4bfb46a15a9b9572abc" FileName="ndmap.edf" Size="44325"/>
    <FileProperties md5="c14a2796b8ae6a14218418edaf822cfc" FileName="ndquest.edf" Size="819413"/>
    <FileProperties md5="7b8c0491abdc98e3e5a59e03c2316c9c" FileName="NDSkillForce.edf" Size="1219977"/>
    <FileProperties md5="d3ba8eeeac159733ef50ba5684d0f7ba" FileName="ndstore.edf" Size="78942"/>
    <FileProperties md5="2f0b90484ab885b3972de82e11d05edf" FileName="RF_WebURL.dat" Size="1796"/>
    <FileProperties md5="d8164d1bc326de54a8934de05b762380" FileName="Tutorial.scp" Size="4742"/>
    <FileProperties md5="76e2f086e2c3fa2bed47065bce90dc91" FileName="WorldMapData.dat" Size="8193"/>
   </Files>
  </FolderProperties>
 </FolderProperties>
 <FolderProperties FolderName="GameData">
  <Folders/>
  <Files>
   <FileProperties md5="7f48f3b21c3a6bcc177ff55f893278ca" FileName="Data001.con" Size="15743228"/>
   <FileProperties md5="d144317e1face9760e1810b3b808b139" FileName="Data002.con" Size="10164108"/>
   <FileProperties md5="7dbd809528f7ff418ddb71d4ffd229ca" FileName="Data003.con" Size="7213676"/>
   <FileProperties md5="55e64d2b631f7d93fb893e4406484ea9" FileName="Data004.con" Size="96904700"/>
   <FileProperties md5="b12bcc66d70cbd210d9b0ad5a980f0bb" FileName="Data005.con" Size="42828"/>
   <FileProperties md5="2cc539e2267b422e75ce7964f48db7f3" FileName="Data006.con" Size="2624188"/>
   <FileProperties md5="84f2d5c2422a07bc5eb5fde6b1f04438" FileName="Data007.con" Size="2499436"/>
   <FileProperties md5="be11a48682f9cf5689f29c458535bde6" FileName="Data008.con" Size="3566204"/>
   <FileProperties md5="46d48267803c53e873021822c3e633c8" FileName="Data008_01.con" Size="94716"/>
   <FileProperties md5="3e92abb3641c58ad227b7d2b2aa249dd" FileName="Data008_02.con" Size="144828"/>
   <FileProperties md5="af06b4e329e962a09e6173b1d24d946d" FileName="Data008_03.con" Size="25116076"/>
  </Files>
 </FolderProperties>
 <FolderProperties FolderName="Item">
  <Folders/>
  <Files/>
  <FolderProperties FolderName="Weapon">
   <Folders/>
   <Files/>
   <FolderProperties FolderName="Tex">
    <Folders/>
    <Files/>
    <FolderProperties FolderName="F">
     <Folders/>
     <Files>
      <FileProperties md5="49a55f491a6d8cf0afd7b184c282a18e" FileName="T_Pickaxe_Banana_D.dds" Size="524416"/>
      <FileProperties md5="220ecf762741a78c1df7d8e73a154e66" FileName="T_Pickaxe_Flamingo_2_D.dds" Size="524416"/>
      <FileProperties md5="89606c8055d96b5ed854f366a61ced9c" FileName="T_Pickaxe_Jellyfish_D.dds" Size="524416"/>
      <FileProperties md5="29283d217ebe11419794bf7abb405ca0" FileName="T_Pickaxe_Miner_D.dds" Size="524416"/>
      <FileProperties md5="11069b4ef81868d3dc9abf01ee9a1c8b" FileName="T_Pickaxe_Palm_Tree_D.dds" Size="524416"/>
     </Files>
    </FolderProperties>
    <FolderProperties FolderName="XMAS">
     <Folders/>
     <Files>
      <FileProperties md5="2c7567f93052bd2e7a2d9297f60ca4a1" FileName="SW_xmas03.dds" Size="174904"/>
     </Files>
    </FolderProperties>
   </FolderProperties>
  </FolderProperties>
 </FolderProperties>
 <FolderProperties FolderName="Map">
  <Folders/>
  <Files/>
  <FolderProperties FolderName="Entity">
   <Folders/>
   <Files/>
   <FolderProperties FolderName="e_midway">
    <Folders/>
    <Files/>
    <FolderProperties FolderName="candy01">
     <Folders/>
     <Files>
      <FileProperties md5="a90b5d944e8a2c11fcf66643f75cee10" FileName="Candy_Cane01_Candy_Cane_baked_0.mst" Size="199"/>
      <FileProperties md5="48af01580be727b32127cc567728efbb" FileName="Candy_Cane01_Candy_Cane_pbr_diffuse.dds" Size="8388736"/>
      <FileProperties md5="1214bebd8d2ba8f6e5c96919b20523d4" FileName="MainMaterial.mst" Size="59"/>
     </Files>
    </FolderProperties>
    <FolderProperties FolderName="candy02">
     <Folders/>
     <Files>
      <FileProperties md5="445c8bb99c849b2aa27b345048c976b7" FileName="Candy_Cane02_Candy_Cane_baked_0.mst" Size="199"/>
      <FileProperties md5="162c5a7fad4c14cda85babf7485e0dc0" FileName="Candy_Cane02_Candy_Cane_pbr_diffuse.dds" Size="8388736"/>
      <FileProperties md5="7c73329894d991e9a6c0660d5f45f83e" FileName="MainMaterial.mst" Size="59"/>
     </Files>
    </FolderProperties>
    <FolderProperties FolderName="candy03">
     <Folders/>
     <Files>
      <FileProperties md5="1ff09e04bfaaef605352fe4e80277923" FileName="Candy_Cane03_Candy_Cane_baked_0.mst" Size="199"/>
      <FileProperties md5="298c57f38b63fea28cdbf7f02232aeca" FileName="Candy_Cane03_Candy_Cane_pbr_diffuse.dds" Size="8388736"/>
      <FileProperties md5="facf7adfe945b03bcb7aa4ad8e3a7f3b" FileName="MainMaterial.mst" Size="59"/>
     </Files>
    </FolderProperties>
    <FolderProperties FolderName="candy04">
     <Folders/>
     <Files>
      <FileProperties md5="9150df460a36d830b1e0ef7d35dbeb89" FileName="Candy_Cane04_Candy_Cane_baked_0.mst" Size="199"/>
      <FileProperties md5="68e336b4a0b4e546ccee3a4e2d817cf1" FileName="Candy_Cane04_Candy_Cane_pbr_diffuse.dds" Size="8388736"/>
      <FileProperties md5="202fb621d23b9d41bd74c42a3fc2bfea" FileName="MainMaterial.mst" Size="59"/>
     </Files>
    </FolderProperties>
    <FolderProperties FolderName="candy05">
     <Folders/>
     <Files>
      <FileProperties md5="84d3019e0f0f289a6f4298f97aef33fc" FileName="Candy_Cane05_Candy_Cane_baked_0.mst" Size="199"/>
      <FileProperties md5="016d6f2b0e121874d438080c0cbe1535" FileName="Candy_Cane05_Candy_Cane_pbr_diffuse.dds" Size="8388736"/>
      <FileProperties md5="7dbdb9a145a268ff797a1223beae65c4" FileName="MainMaterial.mst" Size="59"/>
     </Files>
    </FolderProperties>
    <FolderProperties FolderName="frostivus_tree">
     <Folders/>
     <Files>
      <FileProperties md5="61983a26c8fcc682c74b5b1ee2058366" FileName="frostivus_tree_1.mst" Size="181"/>
      <FileProperties md5="61c0c1d45bc4b2cea6a973670ca581cb" FileName="frostivus_tree_10.dds" Size="32896"/>
      <FileProperties md5="5f41c71d53e4fa264c4ea54e12b1f7a1" FileName="frostivus_tree_12.dds" Size="131200"/>
      <FileProperties md5="d1a5a91775d47da8c4a520d64354a0fd" FileName="frostivus_tree_2.dds" Size="262272"/>
      <FileProperties md5="9ba5e76527cdc26140edf2d96986a02c" FileName="MainMaterial.mst" Size="106"/>
      <FileProperties md5="007f879aa434858534758a3defebbc61" FileName="tree_pine_frond_snow_00b_0.mst" Size="180"/>
      <FileProperties md5="d6a9ee5e6c1e6370cea3ecf049a32c91" FileName="tree_pine_frond_snow_00c_2.mst" Size="181"/>
     </Files>
    </FolderProperties>
    <FolderProperties FolderName="l_tree15-w">
     <Folders/>
     <Files>
      <FileProperties md5="77c6606fde959ed8e7e2baa737709312" FileName="l_tree15-w.r3m" Size="388"/>
      <FileProperties md5="498da42cb21be87b542192e7948ef85d" FileName="l_tree15-w.r3t" Size="524856"/>
     </Files>
    </FolderProperties>
    <FolderProperties FolderName="snowman">
     <Folders/>
     <Files>
      <FileProperties md5="4bec6480a7a9bf805c7e645785838426" FileName="frostivus_snowman_0.dds" Size="131200"/>
      <FileProperties md5="ec95f62674f3fb8ce98ae0581c5d533c" FileName="MainMaterial.mst" Size="44"/>
      <FileProperties md5="3942cc2378ccfe84016ed3c0ea1ef7be" FileName="Material%#613_0.mst" Size="183"/>
     </Files>
    </FolderProperties>
   </FolderProperties>
  </FolderProperties>
  <FolderProperties FolderName="neutralA">
   <Folders/>
   <Files>
    <FileProperties md5="a35f891891a1040b2049d14aeecda5f1" FileName="neutralA.r3x" Size="1028"/>
   </Files>
  </FolderProperties>
  <FolderProperties FolderName="neutralB">
   <Folders/>
   <Files>
    <FileProperties md5="adf6fd465774c752449ae468f1512351" FileName="neutralB.r3x" Size="1028"/>
   </Files>
  </FolderProperties>
  <FolderProperties FolderName="neutralC">
   <Folders/>
   <Files>
    <FileProperties md5="7982f5e5025b29afe2fad234dd9b4a3a" FileName="neutralC.r3x" Size="1028"/>
   </Files>
  </FolderProperties>
  <FolderProperties FolderName="Station_Dome">
   <Folders/>
   <Files>
    <FileProperties md5="736d39edfdc7d7a6b0f3e79b4abeb815" FileName="station_dome.BSP" Size="17957778"/>
    <FileProperties md5="65bf3ba627a1f5dd6cf36eb9e2043f77" FileName="Station_Dome.r3m" Size="169916"/>
    <FileProperties md5="d1067ea3e13a5763032b381632957b05" FileName="Station_Dome.r3t" Size="19477540"/>
    <FileProperties md5="e18ba7a0c66e8cd9a14bd5303c6fb979" FileName="Station_Dome.r3x" Size="1036"/>
    <FileProperties md5="07b56df268fae75816c1ab3a02a82fc6" FileName="station_domeLgt.R3T" Size="9046352"/>
   </Files>
   <FolderProperties FolderName="Sky">
    <Folders/>
    <Files>
     <FileProperties md5="3b5f4aa11dfabaad1dfa42578d7b7c1d" FileName="station_domesky.r3e" Size="153350"/>
     <FileProperties md5="d725ad9b48a28839099314b33a345b33" FileName="station_domesky.r3m" Size="7216"/>
     <FileProperties md5="6987a5b02fd8a88a4c308dd4adfaed86" FileName="station_domesky.r3t" Size="8554240"/>
    </Files>
   </FolderProperties>
  </FolderProperties>
  <FolderProperties FolderName="xmas">
   <Folders/>
   <Files>
    <FileProperties md5="091751f29c048da3f5391eea2c89caed" FileName="xmas.r3x" Size="1028"/>
   </Files>
   <FolderProperties FolderName="Sky">
    <Folders/>
    <Files>
     <FileProperties md5="3b5f4aa11dfabaad1dfa42578d7b7c1d" FileName="xmassky.r3e" Size="153350"/>
     <FileProperties md5="d725ad9b48a28839099314b33a345b33" FileName="xmassky.r3m" Size="7216"/>
     <FileProperties md5="6987a5b02fd8a88a4c308dd4adfaed86" FileName="xmassky.r3t" Size="8554240"/>
    </Files>
   </FolderProperties>
   <FolderProperties FolderName="tex">
    <Folders/>
    <Files>
     <FileProperties md5="e79bee51768218953a0915665919a232" FileName="ice.dds" Size="131200"/>
     <FileProperties md5="764f80325ae7d09ea1ce18713cdef8a2" FileName="MainMaterial.mst" Size="3983"/>
     <FileProperties md5="711f231df97eff57d8fa1318ed877d4d" FileName="Material%#406_100.mst" Size="182"/>
     <FileProperties md5="3b7c1d9862c51f07d1c1900cf32d4aaf" FileName="Material%#407_65.mst" Size="182"/>
     <FileProperties md5="3b7c1d9862c51f07d1c1900cf32d4aaf" FileName="Material%#408_64.mst" Size="182"/>
     <FileProperties md5="3b7c1d9862c51f07d1c1900cf32d4aaf" FileName="Material%#409_97.mst" Size="182"/>
     <FileProperties md5="0cad740e3ff1b51f86e7e0b05b94e235" FileName="Material%#410_77.mst" Size="182"/>
     <FileProperties md5="0cad740e3ff1b51f86e7e0b05b94e235" FileName="Material%#411_76.mst" Size="182"/>
     <FileProperties md5="3b7c1d9862c51f07d1c1900cf32d4aaf" FileName="Material%#416_78.mst" Size="182"/>
     <FileProperties md5="0cad740e3ff1b51f86e7e0b05b94e235" FileName="Material%#419_75.mst" Size="182"/>
     <FileProperties md5="0cad740e3ff1b51f86e7e0b05b94e235" FileName="Material%#420_74.mst" Size="182"/>
     <FileProperties md5="0cad740e3ff1b51f86e7e0b05b94e235" FileName="Material%#421_79.mst" Size="182"/>
     <FileProperties md5="0cad740e3ff1b51f86e7e0b05b94e235" FileName="Material%#422_72.mst" Size="182"/>
     <FileProperties md5="0cad740e3ff1b51f86e7e0b05b94e235" FileName="Material%#423_73.mst" Size="182"/>
     <FileProperties md5="0cad740e3ff1b51f86e7e0b05b94e235" FileName="Material%#424_80.mst" Size="182"/>
     <FileProperties md5="0cad740e3ff1b51f86e7e0b05b94e235" FileName="Material%#425_81.mst" Size="182"/>
     <FileProperties md5="711f231df97eff57d8fa1318ed877d4d" FileName="Material%#427_87.mst" Size="182"/>
     <FileProperties md5="711f231df97eff57d8fa1318ed877d4d" FileName="Material%#428_86.mst" Size="182"/>
     <FileProperties md5="0cad740e3ff1b51f86e7e0b05b94e235" FileName="Material%#429_82.mst" Size="182"/>
     <FileProperties md5="0cad740e3ff1b51f86e7e0b05b94e235" FileName="Material%#430_84.mst" Size="182"/>
     <FileProperties md5="0cad740e3ff1b51f86e7e0b05b94e235" FileName="Material%#431_83.mst" Size="182"/>
     <FileProperties md5="3b7c1d9862c51f07d1c1900cf32d4aaf" FileName="Material%#432_92.mst" Size="182"/>
     <FileProperties md5="3b7c1d9862c51f07d1c1900cf32d4aaf" FileName="Material%#433_91.mst" Size="182"/>
     <FileProperties md5="3b7c1d9862c51f07d1c1900cf32d4aaf" FileName="Material%#434_96.mst" Size="182"/>
     <FileProperties md5="711f231df97eff57d8fa1318ed877d4d" FileName="Material%#436_94.mst" Size="182"/>
     <FileProperties md5="711f231df97eff57d8fa1318ed877d4d" FileName="Material%#437_95.mst" Size="182"/>
     <FileProperties md5="711f231df97eff57d8fa1318ed877d4d" FileName="Material%#438_93.mst" Size="182"/>
     <FileProperties md5="711f231df97eff57d8fa1318ed877d4d" FileName="Material%#439_98.mst" Size="182"/>
     <FileProperties md5="0cad740e3ff1b51f86e7e0b05b94e235" FileName="Material%#446_99.mst" Size="182"/>
     <FileProperties md5="711f231df97eff57d8fa1318ed877d4d" FileName="Material%#447_69.mst" Size="182"/>
     <FileProperties md5="711f231df97eff57d8fa1318ed877d4d" FileName="Material%#448_68.mst" Size="182"/>
     <FileProperties md5="711f231df97eff57d8fa1318ed877d4d" FileName="Material%#449_66.mst" Size="182"/>
     <FileProperties md5="0cad740e3ff1b51f86e7e0b05b94e235" FileName="Material%#450_88.mst" Size="182"/>
     <FileProperties md5="0cad740e3ff1b51f86e7e0b05b94e235" FileName="Material%#451_71.mst" Size="182"/>
     <FileProperties md5="711f231df97eff57d8fa1318ed877d4d" FileName="Material%#455_67.mst" Size="182"/>
     <FileProperties md5="711f231df97eff57d8fa1318ed877d4d" FileName="Material%#456_89.mst" Size="182"/>
     <FileProperties md5="0cad740e3ff1b51f86e7e0b05b94e235" FileName="Material%#458_70.mst" Size="182"/>
     <FileProperties md5="0cad740e3ff1b51f86e7e0b05b94e235" FileName="Material%#459_90.mst" Size="182"/>
     <FileProperties md5="781c48e6fd3b95b23d7e0a86187db5e8" FileName="Material%#460_19.mst" Size="179"/>
     <FileProperties md5="781c48e6fd3b95b23d7e0a86187db5e8" FileName="Material%#461_20.mst" Size="179"/>
     <FileProperties md5="781c48e6fd3b95b23d7e0a86187db5e8" FileName="Material%#462_9.mst" Size="179"/>
     <FileProperties md5="781c48e6fd3b95b23d7e0a86187db5e8" FileName="Material%#463_8.mst" Size="179"/>
     <FileProperties md5="781c48e6fd3b95b23d7e0a86187db5e8" FileName="Material%#464_17.mst" Size="179"/>
     <FileProperties md5="781c48e6fd3b95b23d7e0a86187db5e8" FileName="Material%#465_18.mst" Size="179"/>
     <FileProperties md5="781c48e6fd3b95b23d7e0a86187db5e8" FileName="Material%#466_26.mst" Size="179"/>
     <FileProperties md5="781c48e6fd3b95b23d7e0a86187db5e8" FileName="Material%#467_27.mst" Size="179"/>
     <FileProperties md5="781c48e6fd3b95b23d7e0a86187db5e8" FileName="Material%#468_28.mst" Size="179"/>
     <FileProperties md5="781c48e6fd3b95b23d7e0a86187db5e8" FileName="Material%#469_29.mst" Size="179"/>
     <FileProperties md5="781c48e6fd3b95b23d7e0a86187db5e8" FileName="Material%#470_35.mst" Size="179"/>
     <FileProperties md5="781c48e6fd3b95b23d7e0a86187db5e8" FileName="Material%#471_36.mst" Size="179"/>
     <FileProperties md5="781c48e6fd3b95b23d7e0a86187db5e8" FileName="Material%#472_37.mst" Size="179"/>
     <FileProperties md5="781c48e6fd3b95b23d7e0a86187db5e8" FileName="Material%#473_38.mst" Size="179"/>
     <FileProperties md5="781c48e6fd3b95b23d7e0a86187db5e8" FileName="Material%#474_43.mst" Size="179"/>
     <FileProperties md5="781c48e6fd3b95b23d7e0a86187db5e8" FileName="Material%#475_44.mst" Size="179"/>
     <FileProperties md5="781c48e6fd3b95b23d7e0a86187db5e8" FileName="Material%#476_53.mst" Size="179"/>
     <FileProperties md5="781c48e6fd3b95b23d7e0a86187db5e8" FileName="Material%#477_52.mst" Size="179"/>
     <FileProperties md5="781c48e6fd3b95b23d7e0a86187db5e8" FileName="Material%#478_54.mst" Size="179"/>
     <FileProperties md5="781c48e6fd3b95b23d7e0a86187db5e8" FileName="Material%#479_55.mst" Size="179"/>
     <FileProperties md5="781c48e6fd3b95b23d7e0a86187db5e8" FileName="Material%#480_39.mst" Size="179"/>
     <FileProperties md5="781c48e6fd3b95b23d7e0a86187db5e8" FileName="Material%#481_47.mst" Size="179"/>
     <FileProperties md5="781c48e6fd3b95b23d7e0a86187db5e8" FileName="Material%#482_46.mst" Size="179"/>
     <FileProperties md5="781c48e6fd3b95b23d7e0a86187db5e8" FileName="Material%#483_48.mst" Size="179"/>
     <FileProperties md5="781c48e6fd3b95b23d7e0a86187db5e8" FileName="Material%#484_57.mst" Size="179"/>
     <FileProperties md5="781c48e6fd3b95b23d7e0a86187db5e8" FileName="Material%#485_58.mst" Size="179"/>
     <FileProperties md5="781c48e6fd3b95b23d7e0a86187db5e8" FileName="Material%#486_59.mst" Size="179"/>
     <FileProperties md5="781c48e6fd3b95b23d7e0a86187db5e8" FileName="Material%#487_60.mst" Size="179"/>
     <FileProperties md5="781c48e6fd3b95b23d7e0a86187db5e8" FileName="Material%#488_49.mst" Size="179"/>
     <FileProperties md5="781c48e6fd3b95b23d7e0a86187db5e8" FileName="Material%#489_41.mst" Size="179"/>
     <FileProperties md5="781c48e6fd3b95b23d7e0a86187db5e8" FileName="Material%#490_50.mst" Size="179"/>
     <FileProperties md5="781c48e6fd3b95b23d7e0a86187db5e8" FileName="Material%#491_40.mst" Size="179"/>
     <FileProperties md5="781c48e6fd3b95b23d7e0a86187db5e8" FileName="Material%#492_51.mst" Size="179"/>
     <FileProperties md5="781c48e6fd3b95b23d7e0a86187db5e8" FileName="Material%#493_42.mst" Size="179"/>
     <FileProperties md5="781c48e6fd3b95b23d7e0a86187db5e8" FileName="Material%#494_33.mst" Size="179"/>
     <FileProperties md5="781c48e6fd3b95b23d7e0a86187db5e8" FileName="Material%#495_31.mst" Size="179"/>
     <FileProperties md5="781c48e6fd3b95b23d7e0a86187db5e8" FileName="Material%#496_32.mst" Size="179"/>
     <FileProperties md5="781c48e6fd3b95b23d7e0a86187db5e8" FileName="Material%#497_30.mst" Size="179"/>
     <FileProperties md5="781c48e6fd3b95b23d7e0a86187db5e8" FileName="Material%#498_21.mst" Size="179"/>
     <FileProperties md5="781c48e6fd3b95b23d7e0a86187db5e8" FileName="Material%#499_22.mst" Size="179"/>
     <FileProperties md5="781c48e6fd3b95b23d7e0a86187db5e8" FileName="Material%#500_24.mst" Size="179"/>
     <FileProperties md5="781c48e6fd3b95b23d7e0a86187db5e8" FileName="Material%#501_25.mst" Size="179"/>
     <FileProperties md5="781c48e6fd3b95b23d7e0a86187db5e8" FileName="Material%#502_10.mst" Size="179"/>
     <FileProperties md5="781c48e6fd3b95b23d7e0a86187db5e8" FileName="Material%#503_11.mst" Size="179"/>
     <FileProperties md5="781c48e6fd3b95b23d7e0a86187db5e8" FileName="Material%#504_13.mst" Size="179"/>
     <FileProperties md5="781c48e6fd3b95b23d7e0a86187db5e8" FileName="Material%#505_14.mst" Size="179"/>
     <FileProperties md5="781c48e6fd3b95b23d7e0a86187db5e8" FileName="Material%#506_15.mst" Size="179"/>
     <FileProperties md5="781c48e6fd3b95b23d7e0a86187db5e8" FileName="Material%#507_16.mst" Size="179"/>
     <FileProperties md5="781c48e6fd3b95b23d7e0a86187db5e8" FileName="Material%#508_5.mst" Size="179"/>
     <FileProperties md5="781c48e6fd3b95b23d7e0a86187db5e8" FileName="Material%#509_45.mst" Size="179"/>
     <FileProperties md5="781c48e6fd3b95b23d7e0a86187db5e8" FileName="Material%#510_56.mst" Size="179"/>
     <FileProperties md5="781c48e6fd3b95b23d7e0a86187db5e8" FileName="Material%#511_6.mst" Size="179"/>
     <FileProperties md5="781c48e6fd3b95b23d7e0a86187db5e8" FileName="Material%#512_7.mst" Size="179"/>
     <FileProperties md5="781c48e6fd3b95b23d7e0a86187db5e8" FileName="Material%#513_61.mst" Size="179"/>
     <FileProperties md5="781c48e6fd3b95b23d7e0a86187db5e8" FileName="Material%#514_3.mst" Size="179"/>
     <FileProperties md5="781c48e6fd3b95b23d7e0a86187db5e8" FileName="Material%#515_23.mst" Size="179"/>
     <FileProperties md5="781c48e6fd3b95b23d7e0a86187db5e8" FileName="Material%#516_34.mst" Size="179"/>
     <FileProperties md5="781c48e6fd3b95b23d7e0a86187db5e8" FileName="Material%#517_4.mst" Size="179"/>
     <FileProperties md5="781c48e6fd3b95b23d7e0a86187db5e8" FileName="Material%#518_62.mst" Size="179"/>
     <FileProperties md5="781c48e6fd3b95b23d7e0a86187db5e8" FileName="Material%#519_0.mst" Size="179"/>
     <FileProperties md5="781c48e6fd3b95b23d7e0a86187db5e8" FileName="Material%#520_1.mst" Size="179"/>
     <FileProperties md5="781c48e6fd3b95b23d7e0a86187db5e8" FileName="Material%#521_2.mst" Size="179"/>
     <FileProperties md5="781c48e6fd3b95b23d7e0a86187db5e8" FileName="Material%#522_63.mst" Size="179"/>
     <FileProperties md5="781c48e6fd3b95b23d7e0a86187db5e8" FileName="Material%#523_12.mst" Size="179"/>
     <FileProperties md5="64ab967c4f2f840331b11e40a995ac9a" FileName="Material%#526_117.mst" Size="185"/>
     <FileProperties md5="a15e82c82cebe5164641894ad2b36aa6" FileName="Material%#527_164.mst" Size="183"/>
     <FileProperties md5="85c47691eef299aa5fd94be7c578ea90" FileName="Material%#528_114.mst" Size="191"/>
     <FileProperties md5="73b2b8ad7da1f517fc92d8f3029a1c3b" FileName="Material%#529_115.mst" Size="180"/>
     <FileProperties md5="64ab967c4f2f840331b11e40a995ac9a" FileName="Material%#530_116.mst" Size="185"/>
     <FileProperties md5="73b2b8ad7da1f517fc92d8f3029a1c3b" FileName="Material%#534_111.mst" Size="180"/>
     <FileProperties md5="64ab967c4f2f840331b11e40a995ac9a" FileName="Material%#535_113.mst" Size="185"/>
     <FileProperties md5="64ab967c4f2f840331b11e40a995ac9a" FileName="Material%#536_112.mst" Size="185"/>
     <FileProperties md5="64ab967c4f2f840331b11e40a995ac9a" FileName="Material%#540_109.mst" Size="185"/>
     <FileProperties md5="64ab967c4f2f840331b11e40a995ac9a" FileName="Material%#541_108.mst" Size="185"/>
     <FileProperties md5="cac4953c386b105861f1b9dfd0ee7245" FileName="Material%#542_152.mst" Size="187"/>
     <FileProperties md5="cac4953c386b105861f1b9dfd0ee7245" FileName="Material%#543_153.mst" Size="187"/>
     <FileProperties md5="cac4953c386b105861f1b9dfd0ee7245" FileName="Material%#546_154.mst" Size="187"/>
     <FileProperties md5="cac4953c386b105861f1b9dfd0ee7245" FileName="Material%#547_155.mst" Size="187"/>
     <FileProperties md5="cac4953c386b105861f1b9dfd0ee7245" FileName="Material%#548_159.mst" Size="187"/>
     <FileProperties md5="cac4953c386b105861f1b9dfd0ee7245" FileName="Material%#549_158.mst" Size="187"/>
     <FileProperties md5="cac4953c386b105861f1b9dfd0ee7245" FileName="Material%#550_157.mst" Size="187"/>
     <FileProperties md5="cac4953c386b105861f1b9dfd0ee7245" FileName="Material%#551_156.mst" Size="187"/>
     <FileProperties md5="73b2b8ad7da1f517fc92d8f3029a1c3b" FileName="Material%#553_107.mst" Size="180"/>
     <FileProperties md5="73b2b8ad7da1f517fc92d8f3029a1c3b" FileName="Material%#554_103.mst" Size="180"/>
     <FileProperties md5="73b2b8ad7da1f517fc92d8f3029a1c3b" FileName="Material%#555_127.mst" Size="180"/>
     <FileProperties md5="73b2b8ad7da1f517fc92d8f3029a1c3b" FileName="Material%#556_131.mst" Size="180"/>
     <FileProperties md5="73b2b8ad7da1f517fc92d8f3029a1c3b" FileName="Material%#557_119.mst" Size="180"/>
     <FileProperties md5="73b2b8ad7da1f517fc92d8f3029a1c3b" FileName="Material%#558_123.mst" Size="180"/>
     <FileProperties md5="73b2b8ad7da1f517fc92d8f3029a1c3b" FileName="Material%#560_139.mst" Size="180"/>
     <FileProperties md5="73b2b8ad7da1f517fc92d8f3029a1c3b" FileName="Material%#561_135.mst" Size="180"/>
     <FileProperties md5="73b2b8ad7da1f517fc92d8f3029a1c3b" FileName="Material%#563_143.mst" Size="180"/>
     <FileProperties md5="64ab967c4f2f840331b11e40a995ac9a" FileName="Material%#564_144.mst" Size="185"/>
     <FileProperties md5="64ab967c4f2f840331b11e40a995ac9a" FileName="Material%#565_145.mst" Size="185"/>
     <FileProperties md5="64ab967c4f2f840331b11e40a995ac9a" FileName="Material%#567_136.mst" Size="185"/>
     <FileProperties md5="64ab967c4f2f840331b11e40a995ac9a" FileName="Material%#568_137.mst" Size="185"/>
     <FileProperties md5="64ab967c4f2f840331b11e40a995ac9a" FileName="Material%#569_140.mst" Size="185"/>
     <FileProperties md5="64ab967c4f2f840331b11e40a995ac9a" FileName="Material%#570_141.mst" Size="185"/>
     <FileProperties md5="64ab967c4f2f840331b11e40a995ac9a" FileName="Material%#571_121.mst" Size="185"/>
     <FileProperties md5="64ab967c4f2f840331b11e40a995ac9a" FileName="Material%#572_120.mst" Size="185"/>
     <FileProperties md5="64ab967c4f2f840331b11e40a995ac9a" FileName="Material%#573_125.mst" Size="185"/>
     <FileProperties md5="64ab967c4f2f840331b11e40a995ac9a" FileName="Material%#574_124.mst" Size="185"/>
     <FileProperties md5="64ab967c4f2f840331b11e40a995ac9a" FileName="Material%#575_129.mst" Size="185"/>
     <FileProperties md5="64ab967c4f2f840331b11e40a995ac9a" FileName="Material%#576_128.mst" Size="185"/>
     <FileProperties md5="64ab967c4f2f840331b11e40a995ac9a" FileName="Material%#577_132.mst" Size="185"/>
     <FileProperties md5="64ab967c4f2f840331b11e40a995ac9a" FileName="Material%#578_133.mst" Size="185"/>
     <FileProperties md5="64ab967c4f2f840331b11e40a995ac9a" FileName="Material%#579_104.mst" Size="185"/>
     <FileProperties md5="64ab967c4f2f840331b11e40a995ac9a" FileName="Material%#580_105.mst" Size="185"/>
     <FileProperties md5="a15e82c82cebe5164641894ad2b36aa6" FileName="Material%#581_163.mst" Size="183"/>
     <FileProperties md5="a15e82c82cebe5164641894ad2b36aa6" FileName="Material%#582_160.mst" Size="183"/>
     <FileProperties md5="a15e82c82cebe5164641894ad2b36aa6" FileName="Material%#583_161.mst" Size="183"/>
     <FileProperties md5="a15e82c82cebe5164641894ad2b36aa6" FileName="Material%#584_162.mst" Size="183"/>
     <FileProperties md5="85c47691eef299aa5fd94be7c578ea90" FileName="Material%#585_106.mst" Size="191"/>
     <FileProperties md5="85c47691eef299aa5fd94be7c578ea90" FileName="Material%#586_110.mst" Size="191"/>
     <FileProperties md5="85c47691eef299aa5fd94be7c578ea90" FileName="Material%#587_102.mst" Size="191"/>
     <FileProperties md5="85c47691eef299aa5fd94be7c578ea90" FileName="Material%#588_126.mst" Size="191"/>
     <FileProperties md5="85c47691eef299aa5fd94be7c578ea90" FileName="Material%#589_122.mst" Size="191"/>
     <FileProperties md5="85c47691eef299aa5fd94be7c578ea90" FileName="Material%#590_118.mst" Size="191"/>
     <FileProperties md5="85c47691eef299aa5fd94be7c578ea90" FileName="Material%#591_134.mst" Size="191"/>
     <FileProperties md5="85c47691eef299aa5fd94be7c578ea90" FileName="Material%#592_138.mst" Size="191"/>
     <FileProperties md5="85c47691eef299aa5fd94be7c578ea90" FileName="Material%#593_142.mst" Size="191"/>
     <FileProperties md5="f222b82879857d5d0b5e4fa27106a088" FileName="Material%#594_148.mst" Size="214"/>
     <FileProperties md5="85c47691eef299aa5fd94be7c578ea90" FileName="Material%#595_130.mst" Size="191"/>
     <FileProperties md5="f553d0e0b3c0e10eb2f44dd51b203fa7" FileName="Material%#596_167.mst" Size="166"/>
     <FileProperties md5="9eb23713a92b6caf233cc9e3b4537ed6" FileName="Material%#597_168.mst" Size="191"/>
     <FileProperties md5="566038c4d3b6c3100e189686ae1dfb8c" FileName="Material%#599_169.mst" Size="191"/>
     <FileProperties md5="f6db87c3e5f20957a08eeea5dbc52e45" FileName="Material%#603_170.mst" Size="176"/>
     <FileProperties md5="31d1ff1a1e7927eb8fa4f72b7da634fb" FileName="Material%#610_171.mst" Size="176"/>
     <FileProperties md5="781c48e6fd3b95b23d7e0a86187db5e8" FileName="Material%#612_54.mst" Size="179"/>
     <FileProperties md5="0828d9b82c3246e6f745b952dee7b9d0" FileName="MI_brick_tiles_Inst_146.mst" Size="204"/>
     <FileProperties md5="12eb3d9a8b0158a66b4ab2666d5e8f66" FileName="MI_brick_tiles_Inst_MI_brick_tiles_Inst_D.dds" Size="131200"/>
     <FileProperties md5="1be960b70da63f318e0a9299395e013e" FileName="MI_broken_bricks_Inst_165.mst" Size="208"/>
     <FileProperties md5="a77e56f7353903457daa24dd5c921a09" FileName="MI_broken_bricks_Inst_MI_broken_bricks_Inst_D.dds" Size="131200"/>
     <FileProperties md5="8a29a9284a1ce80bf78c4de4a77a624f" FileName="MI_cliff_b_Inst_85.mst" Size="196"/>
     <FileProperties md5="fe86e1064c0e0281ee77f2dcc736afc1" FileName="MI_cliff_b_Inst_MI_cliff_b_Inst_D.dds" Size="131200"/>
     <FileProperties md5="0e7999c590973c5195c4cd9a2b121ca0" FileName="MI_column_Inst_151.mst" Size="194"/>
     <FileProperties md5="0c0b0db1fef40a68fd9300368ba13ed2" FileName="MI_column_Inst_MI_column_Inst_D.dds" Size="131200"/>
     <FileProperties md5="0e8a8d4b2ad0247fc9c24278d269154b" FileName="MI_corner_block_Inst_150.mst" Size="206"/>
     <FileProperties md5="83978373ba0ffb871a137f10274c4c7c" FileName="MI_corner_block_Inst_MI_corner_block_Inst_D.dds" Size="131200"/>
     <FileProperties md5="797e7f1a96eed528d3760bc4d64a8cc7" FileName="MI_fireball_B_Inst_166.mst" Size="202"/>
     <FileProperties md5="4edb9931ca677fb27c9bbb5a2c2c5f21" FileName="MI_fireball_B_Inst_MI_fireball_B_Inst_D.dds" Size="136"/>
     <FileProperties md5="74856ffb3e8713401aa86c233835795b" FileName="MI_ruins_a_Inst_149.mst" Size="196"/>
     <FileProperties md5="ea8c56cf54a787ca65c55d93dd8e19c7" FileName="MI_ruins_a_Inst_MI_ruins_a_Inst_D.dds" Size="131200"/>
     <FileProperties md5="c9a7abb0f30f0f03bbe3df0407146497" FileName="MI_sacrifices_plate_Inst_MI_sacrifices_plate_Inst_D.dds" Size="131200"/>
     <FileProperties md5="97481a594f2c06e19fdaff05c6936bd7" FileName="MI_stairs_Inst_101.mst" Size="194"/>
     <FileProperties md5="f0f13614105f3a6e4b0e84e74ef8e090" FileName="MI_stairs_Inst_MI_stairs_Inst_D.dds" Size="131200"/>
     <FileProperties md5="c3a825d40de82e560dd71fbc94d8f0f6" FileName="MI_tile_ornament_Inst_147.mst" Size="208"/>
     <FileProperties md5="fa832d6519f3a1f0c1fb0f0d1059d327" FileName="MI_tile_ornament_Inst_MI_tile_ornament_Inst_D.dds" Size="131200"/>
     <FileProperties md5="4278b1484e33f29824bd30177012404f" FileName="present_model.dds" Size="524416"/>
     <FileProperties md5="e5ac4bc84c60070e85099fdcb311339e" FileName="tuskhouse01_0.dds" Size="131200"/>
     <FileProperties md5="f12c226040cde4986810d27587eb8a8f" FileName="T_chains_fence_BaseColor.dds" Size="131200"/>
     <FileProperties md5="c86d9c4475e4ca68ca32cc9abf7c9cfe" FileName="T_cliff_a_BaseColor.dds" Size="524416"/>
     <FileProperties md5="1cf6091b67590f59a409eb2aa2d6edeb" FileName="T_cliff_c_BaseColor.dds" Size="131200"/>
     <FileProperties md5="f91a27a8b2c5ff99ae51e073e36d9593" FileName="T_cliff_d_BaseColor.dds" Size="524416"/>
     <FileProperties md5="aa04b65797cbd1f249be0e174382b3c3" FileName="T_fence_BaseColor.dds" Size="131200"/>
     <FileProperties md5="91ff578f2d5659c63da6e0097c6cb0f6" FileName="T_fence_ruin_BaseColor.dds" Size="131200"/>
     <FileProperties md5="4980e408f75670308cb468259caf450c" FileName="T_lamppost_BaseColor.dds" Size="131200"/>
     <FileProperties md5="c381e8b4fa4837200646b176501a93ed" FileName="T_PolygonFantasyKingdom_01_A.dds" Size="524416"/>
     <FileProperties md5="1d0e0bc0e30e31babffe0952e19c7c5a" FileName="T_snow_basecolor.dds" Size="131200"/>
     <FileProperties md5="af10570eae6b85d6b4acdca744070b2e" FileName="T_stone_foundation_BaseColor.dds" Size="131200"/>
    </Files>
   </FolderProperties>
  </FolderProperties>
 </FolderProperties>
 <FolderProperties FolderName="System">
  <Folders/>
  <Files>
   <FileProperties md5="4b055cf1503aa54489f03f32b07c7845" FileName="gui.dll" Size="67126828"/>
   <FileProperties md5="e6b15e5062d0591729e3765d335b1039" FileName="titlelogo.tga" Size="5440044"/>
  </Files>
 </FolderProperties>
</FolderProperties>
